<?xml version = '1.0' encoding = 'UTF-8'?>
<Relation class="oracle.dbtools.crest.model.design.logical.Relation" name="Relation_20" directorySegmentName="seg_0" id="E0CE9720-3813-228A-08DC-AEBFA69D2BA2">
<createdBy>David</createdBy>
<createdTime>2019-09-28 04:51:19 UTC</createdTime>
<ownerDesignName>LABORATORIO_LOGICOL</ownerDesignName>
<engineerTo>
<item key="984DA05F-165E-D772-1948-CA9B2DB15C11" value="true"/>
</engineerTo>
<identifying>false</identifying>
<optionalSource>true</optionalSource>
<optionalTarget>false</optionalTarget>
<sourceCardinality>*</sourceCardinality>
<sourceEntity>32E9F343-66F6-AA21-351E-E8FF0D3D6CEF</sourceEntity>
<targetCardinalityString>*</targetCardinalityString>
<targetEntity>C5E7FA04-A3C7-3584-B6D8-B83B7406F700</targetEntity>
<transferable>true</transferable>
<deleteRule>NO ACTION</deleteRule>
</Relation>